Metadata-Version: 1.0
Name: dz-distributions
Version: 0.1
Summary: Gaussian distributions
Home-page: UNKNOWN
Author: Daniel Zapata
Author-email: danielrzapatas@gmail.com
License: UNKNOWN
Platform: UNKNOWN
